competitions_match-0.3-py2.7-nspkg.pth
competitions/match/__init__.py
competitions/match/default/SimpleMatch.py
competitions/match/default/TestMatch.py
competitions/match/default/__init__.py
competitions_match-0.3.dist-info/METADATA
competitions_match-0.3.dist-info/DESCRIPTION.rst
competitions_match-0.3.dist-info/RECORD
competitions_match-0.3.dist-info/WHEEL
competitions_match-0.3.dist-info/top_level.txt
competitions_match-0.3.dist-info/namespace_packages.txt
competitions_match-0.3.dist-info/metadata.json
