Metadata-Version: 2.0
Name: competitions-match
Version: 0.3
Summary: competitions support library for matches
Home-page: https://github.com/happy5214/competitions-match
Author: Alexander Jones
Author-email: happy5214@gmail.com
License: LGPLv3+
Keywords: competitions matches
Platform: UNKNOWN
Classifier: Development Status :: 3 - Alpha
Classifier: License :: OSI Approved :: GNU Lesser General Public License v3 or later (LGPLv3+)
Classifier: Programming Language :: Python :: 2.7
Classifier: Programming Language :: Python :: 3.2
Classifier: Programming Language :: Python :: 3.3
Classifier: Programming Language :: Python :: 3.4
Classifier: Programming Language :: Python :: 3.5
Classifier: Programming Language :: Python :: 3.6
